AUTHORS
ChangeLog
LICENSE
README.md
renovate.json
requirements.txt
setup.cfg
setup.py
test-requirements.txt
.github/workflows/periodic.yml
.github/workflows/release.yml
.github/workflows/test.yml
desidulate/fileio.py
desidulate/gensidinfo.py
desidulate/getsidinfo.py
desidulate/indexssf.py
desidulate/reg2ssf.py
desidulate/reg2wav.py
desidulate/sidinfo.py
desidulate/sidinfo2dumpcmd.py
desidulate/sidinfoargs.py
desidulate/sidlib.py
desidulate/sidmidi.py
desidulate/sidwav.py
desidulate/sidwrap.py
desidulate/ssf.py
desidulate/ssf2midi.py
desidulate/ssf2swi.py
desidulate/ssf2wav.py
desidulate/swilib.py
desidulate.egg-info/PKG-INFO
desidulate.egg-info/SOURCES.txt
desidulate.egg-info/dependency_links.txt
desidulate.egg-info/entry_points.txt
desidulate.egg-info/not-zip-safe
desidulate.egg-info/pbr.json
desidulate.egg-info/requires.txt
desidulate.egg-info/top_level.txt
docs/desidulate-pipeline.dia
docs/desidulate-pipeline.png
docs/swishot.png
magenta/Dockerfile
tests/e2e.sh
tests/test_sidinfo.py
tests/test_sidlib.py
tests/test_sidwav.py
tests/test_ssf.py
tests/test_swi.py
utils/mididemux.py
utils/plotwav.sh